unfold/__init__.py
unfold/brightway25_export.py
unfold/brightway2_export.py
unfold/data_cleaning.py
unfold/fold.py
unfold/unfold.py
unfold/utils.py
unfold/data/flows_biosphere_38.csv
unfold/data/outdated_flows.yaml
unfold/data/outdated_units.yaml
unfold-1.2.2.dist-info/LICENSE
unfold-1.2.2.dist-info/METADATA
unfold-1.2.2.dist-info/WHEEL
unfold-1.2.2.dist-info/top_level.txt
unfold-1.2.2.dist-info/RECORD
