Metadata-Version: 2.1
Name: unfold
Version: 1.2.2
Summary: Unpacks LCA scenario databases.
Home-page: https://github.com/polca/premise
Author: Romain Sacchi <romain.sacchi@psi.ch>
License:                     GNU AFFERO GENERAL PUBLIC LICENSE
Classifier: Intended Audience :: End Users/Desktop
Classifier: Intended Audience :: Developers
Classifier: Intended Audience :: Science/Research
Classifier: License :: OSI Approved :: BSD License
Classifier: Operating System :: MacOS :: MacOS X
Classifier: Operating System :: Microsoft :: Windows
Classifier: Operating System :: POSIX
Classifier: Programming Language :: Python
Classifier: Programming Language :: Python :: 3
Classifier: Programming Language :: Python :: 3.9
Classifier: Topic :: Scientific/Engineering :: Information Analysis
Classifier: Topic :: Scientific/Engineering :: Mathematics
Classifier: Topic :: Scientific/Engineering :: Visualization
Requires-Python: >=3.10
License-File: LICENSE
Requires-Dist: numpy<2.0.0
Requires-Dist: pandas
Requires-Dist: bw2io
Requires-Dist: bw2data
Requires-Dist: bw2calc
Requires-Dist: prettytable
Requires-Dist: datapackage
Requires-Dist: sparse
Requires-Dist: scipy
Requires-Dist: pyyaml
Requires-Dist: wurst>=0.4.0
Requires-Dist: pyprind
